{
    "bg": "#1e1e2e",
    "fg": "#cdd6f4",
    "color0": "#45475a",
    "color1": "#f38ba8",
    "color2": "#a6e3a1",
    "color3": "#f9e2af",
    "color4": "#89b4fa",
    "color5": "#f5c2e7",
    "color6": "#94e2d5",
    "color7": "#bac2de",
    "color8": "#585b70",
    "color9": "#d20f39",
    "color10": "#40a02b",
    "color11": "#df8e1d",
    "color12": "#1e66f5",
    "color13": "#ea76cb",
    "color14": "#179299",
    "color15": "#bcc0cc",
    "gtk_theme": "Catppuccin-Mocha-B",
    "gtk_icon": "Catppuccin-Mocha",
    "gtk_cursor": "Adwaita",
    "color_cava_1": "#94e2d5",
    "color_cava_2": "#89dceb",
    "color_cava_3": "#74c7ec",
    "color_cava_4": "#89b4fa",
    "color_cava_5": "#cba6f7",
    "color_cava_6": "#f5c2e7",
    "color_cava_7": "#eba0ac",
    "color_cava_8": "#f38ba8",
    "btop_theme": "elementarish",
    "bat_theme": "Catppuccin-mocha",
    "zathura_theme": "catppuccin-mocha",
    "spicetify_theme": "catppuccin-mocha",
    "spicetify_color_scheme": "lavender",
    "nvim_theme": "catppuccin"
}
